heare
