Metadata-Version: 2.4
Name: heare-stats-client
Version: 0.0.10
Summary: Metrics client and server for heare services and clients
Home-page: https://github.com/heare-io/heare-stats-client
Author: Sean Fitzgerald
Author-email: seanfitz@heare.io
Project-URL: Bug Tracker, https://github.com/heare-io/heare-stats-client/issues
Classifier: Programming Language :: Python :: 3
Classifier: License :: OSI Approved :: GNU Lesser General Public License v3 (LGPLv3)
Classifier: Operating System :: OS Independent
Requires-Python: >=3.6
Requires-Dist: heare-config>=1.0.1
Requires-Dist: requests>=2.20
Requires-Dist: websocket-client>=1.2.3
Requires-Dist: pyee>=8.2.2
Requires-Dist: statsd>=4.0.1
